setup.py
tofab/__init__.py
tofab.egg-info/PKG-INFO
tofab.egg-info/SOURCES.txt
tofab.egg-info/dependency_links.txt
tofab.egg-info/requires.txt
tofab.egg-info/top_level.txt