Metadata-Version: 1.1
Name: tofab
Version: 0.2
Summary: Fabric utils, intend to use with Tokit.
Home-page: https://github.com/manhgd/tofab
Author: Giang Manh
Author-email: manhgd@yahoo.com
License: UNKNOWN
Download-URL: https://github.com/manhgd/tofab/tarball/0.2
Keywords: fabric,tokit,tornado
Platform: UNKNOWN
Classifier: Programming Language :: Python :: 2.7
